pyJianYingPro/__init__.py
pyJianYingPro/animation.py
pyJianYingPro/audio_segment.py
pyJianYingPro/draft_content_template.json
pyJianYingPro/draft_folder.py
pyJianYingPro/effect_segment.py
pyJianYingPro/exceptions.py
pyJianYingPro/jianying_controller.py
pyJianYingPro/keyframe.py
pyJianYingPro/local_materials.py
pyJianYingPro/script_file.py
pyJianYingPro/segment.py
pyJianYingPro/template_mode.py
pyJianYingPro/text_segment.py
pyJianYingPro/time_util.py
pyJianYingPro/track.py
pyJianYingPro/util.py
pyJianYingPro/video_segment.py
pyJianYingPro/metadata/__init__.py
pyJianYingPro/metadata/animation_meta.py
pyJianYingPro/metadata/audio_effect_meta.py
pyJianYingPro/metadata/effect_meta.py
pyJianYingPro/metadata/filter_meta.py
pyJianYingPro/metadata/font_meta.py
pyJianYingPro/metadata/mask_meta.py
pyJianYingPro/metadata/transition_meta.py
pyJianYingPro/metadata/video_effect_meta.py
pyjianyingpro-0.1.1.dist-info/METADATA
pyjianyingpro-0.1.1.dist-info/WHEEL
pyjianyingpro-0.1.1.dist-info/top_level.txt
pyjianyingpro-0.1.1.dist-info/RECORD
